vacanthouse.py
vacanthouse-0.0.8.dist-info/METADATA
vacanthouse-0.0.8.dist-info/WHEEL
vacanthouse-0.0.8.dist-info/entry_points.txt
vacanthouse-0.0.8.dist-info/top_level.txt
vacanthouse-0.0.8.dist-info/RECORD
